README.md
setup.py
zenlite/__init__.py
zenlite/assets/logo_32x.ico
zenlite/assets/shaders/zen01.frag
zenlite/assets/shaders/zen01.vert
zenlite/assets/shaders/zen02.frag
zenlite/assets/shaders/zen02.vert
zenlite/assets/textures/wall001.png
zenlite/assets/textures/zenblack.png
zenlite/assets/textures/zenwhite.png
zenlite/core/__init__.py
zenlite/core/globs.py
zenlite/core/zengl.py
zenlite/core/zenprofiler.py
zenlite/core/process/__init__.py
zenlite/core/process/event.py
zenlite/core/process/render.py
zenlite/core/resource/__init__.py
zenlite/core/resource/zencam3D.py
zenlite/core/resource/zenmesh.py
zenlite/core/resource/zenshader.py
zenlite/core/resource/zentexture.py
zenlite/core/resource/zvxbank.py
zenlite/core/zenvx/__init__.py
zenlite/core/zenvx/zvxchunk.py
zenlite/core/zenvx/zvxrealm.py
zenlite/core/zenvx/zvxterrain.py
zenlite/zapplication/__init__.py
zenlite/zplatform/__init__.py
zenlite_DEV.egg-info/PKG-INFO
zenlite_DEV.egg-info/SOURCES.txt
zenlite_DEV.egg-info/dependency_links.txt
zenlite_DEV.egg-info/requires.txt
zenlite_DEV.egg-info/top_level.txt