Metadata-Version: 2.1
Name: zenlite_DEV
Version: 1.0.2024.post30
Summary: the python voxel engine
Home-page: https://github.com/stozak/zenlite
Author: Izaiyah Stokes
Author-email: zeroth.bat@gmail.com
Classifier: Programming Language :: Python :: 3.12
Classifier: License :: OSI Approved :: MIT License
Classifier: Operating System :: OS Independent
Requires-Dist: ipdb
Requires-Dist: GLFW
Requires-Dist: Numba
Requires-Dist: Numpy
Requires-Dist: PyGLM
Requires-Dist: ModernGL
Requires-Dist: objgraph
Requires-Dist: memory_profiler
